videopython/__init__.py
videopython/py.typed
videopython/ai/__init__.py
videopython/ai/backends.py
videopython/ai/config.py
videopython/ai/exceptions.py
videopython/ai/transforms.py
videopython/ai/dubbing/__init__.py
videopython/ai/dubbing/dubber.py
videopython/ai/dubbing/models.py
videopython/ai/dubbing/pipeline.py
videopython/ai/dubbing/timing.py
videopython/ai/generation/__init__.py
videopython/ai/generation/audio.py
videopython/ai/generation/image.py
videopython/ai/generation/translation.py
videopython/ai/generation/video.py
videopython/ai/swapping/__init__.py
videopython/ai/swapping/inpainter.py
videopython/ai/swapping/models.py
videopython/ai/swapping/segmenter.py
videopython/ai/swapping/swapper.py
videopython/ai/understanding/__init__.py
videopython/ai/understanding/audio.py
videopython/ai/understanding/detection.py
videopython/ai/understanding/image.py
videopython/ai/understanding/motion.py
videopython/ai/understanding/separation.py
videopython/ai/understanding/temporal.py
videopython/base/__init__.py
videopython/base/combine.py
videopython/base/description.py
videopython/base/effects.py
videopython/base/exceptions.py
videopython/base/scene.py
videopython/base/transforms.py
videopython/base/transitions.py
videopython/base/utils.py
videopython/base/video.py
videopython/base/audio/__init__.py
videopython/base/audio/analysis.py
videopython/base/audio/audio.py
videopython/base/text/__init__.py
videopython/base/text/overlay.py
videopython/base/text/transcription.py
videopython-0.16.1.dist-info/METADATA
videopython-0.16.1.dist-info/WHEEL
videopython-0.16.1.dist-info/licenses/LICENSE
videopython-0.16.1.dist-info/RECORD
