Metadata-Version: 2.4
Name: videopython
Version: 0.16.1
Summary: Minimal video generation and processing library.
Project-URL: Homepage, https://videopython.com
Project-URL: Repository, https://github.com/bartwojtowicz/videopython/
Project-URL: Documentation, https://videopython.com
Author-email: Bartosz Wójtowicz <bartoszwojtowicz@outlook.com>, Bartosz Rudnikowicz <bartoszrudnikowicz840@gmail.com>, Piotr Pukisz <piotr.pukisz@gmail.com>
License: Apache-2.0
License-File: LICENSE
Keywords: ai,editing,generation,movie,opencv,python,shorts,video,videopython
Classifier: License :: OSI Approved :: Apache Software License
Classifier: Operating System :: OS Independent
Classifier: Programming Language :: Python :: 3
Classifier: Programming Language :: Python :: 3.10
Classifier: Programming Language :: Python :: 3.11
Classifier: Programming Language :: Python :: 3.12
Requires-Python: <3.13,>=3.10
Requires-Dist: numpy>=1.25.2
Requires-Dist: opencv-python>=4.9.0.80
Requires-Dist: pillow>=10.3.0
Requires-Dist: torchcodec>=0.9.1
Requires-Dist: tqdm>=4.66.3
Provides-Extra: ai
Requires-Dist: accelerate>=0.29.2; extra == 'ai'
Requires-Dist: coqui-tts>=0.24.0; extra == 'ai'
Requires-Dist: demucs>=4.0.0; extra == 'ai'
Requires-Dist: diffusers>=0.26.3; extra == 'ai'
Requires-Dist: easyocr>=1.7.0; extra == 'ai'
Requires-Dist: elevenlabs>=1.0.0; extra == 'ai'
Requires-Dist: google-generativeai>=0.8.0; extra == 'ai'
Requires-Dist: hf-transfer>=0.1.9; extra == 'ai'
Requires-Dist: httpx>=0.27.0; extra == 'ai'
Requires-Dist: lumaai>=1.0.0; extra == 'ai'
Requires-Dist: numba>=0.61.0; extra == 'ai'
Requires-Dist: ollama>=0.4.5; extra == 'ai'
Requires-Dist: openai-whisper>=20240930; extra == 'ai'
Requires-Dist: openai>=1.0.0; extra == 'ai'
Requires-Dist: replicate>=0.20.0; extra == 'ai'
Requires-Dist: requests>=2.28.0; extra == 'ai'
Requires-Dist: runwayml>=0.10.0; extra == 'ai'
Requires-Dist: scikit-learn>=1.3.0; extra == 'ai'
Requires-Dist: scipy>=1.10.0; extra == 'ai'
Requires-Dist: torch>=2.1.0; extra == 'ai'
Requires-Dist: transformers>=4.38.1; extra == 'ai'
Requires-Dist: transnetv2-pytorch>=1.0.5; extra == 'ai'
Requires-Dist: ultralytics>=8.0.0; extra == 'ai'
Requires-Dist: whisperx>=3.4.2; extra == 'ai'
Provides-Extra: dev
Requires-Dist: mypy>=1.8.0; extra == 'dev'
Requires-Dist: pytest-cov>=6.1.1; extra == 'dev'
Requires-Dist: pytest>=7.4.0; extra == 'dev'
Requires-Dist: ruff>=0.1.14; extra == 'dev'
Requires-Dist: types-pillow>=10.2.0.20240213; extra == 'dev'
Requires-Dist: types-tqdm>=4.66.0.20240106; extra == 'dev'
